dash_latex/DashLatex.py
dash_latex/__init__.py
dash_latex/_imports_.py
dash_latex/dash_latex.min.js
dash_latex/dash_latex.min.js.map
dash_latex/metadata.json
dash_latex/package-info.json
dash_latex-0.1.1.dist-info/LICENSE
dash_latex-0.1.1.dist-info/METADATA
dash_latex-0.1.1.dist-info/WHEEL
dash_latex-0.1.1.dist-info/top_level.txt
dash_latex-0.1.1.dist-info/RECORD
