Metadata-Version: 2.1
Name: dash-latex
Version: 0.1.1
Summary: A Dash wrapper around React Latex
Home-page: UNKNOWN
Author: Nathan Drezner <nathan@drezner.xyz>
License: UNKNOWN
Platform: UNKNOWN
Classifier: Framework :: Dash
